<?xml version="1.0" encoding="UTF-8" standalone="yes"?>
<addons>
<addon id="p2p.ike" name="[COLOR cyan]P2p.Fix.ike[/COLOR]" version="1.0.3" provider-name="[COLOR wite]Ike[/COLOR]">
  <requires>
    <import addon="xbmc.python" version="2.1.0"/>
  </requires>
  <extension point="xbmc.python.pluginsource" library="default.py">
        <provides>program executable</provides>
  </extension>
  <extension point="xbmc.addon.metadata">
    <summary lang="en">P2p.Fix</summary>
    <description lang="en">P2p.Fix</description>
    <platform>all</platform>
  </extension>
</addon>

<addon id="plugin.program.ike.clean"
       name="Ike.Clean"
       version="1.2"
       provider-name="Ike">
  <requires>
    <import addon="xbmc.python" version="2.1.0"/>
  </requires>
 	<extension point="xbmc.python.pluginsource" library="default.py">
		<provides>executable</provides>
	</extension>
  <extension point="xbmc.service" library="service.py" start="startup" />
  <extension point="xbmc.addon.metadata">
    <platform>all</platform>
    <summary>Manutenção</summary>
    <description>Programa para uso exclusivo do Addon Ike.
	Ezy-Fork</description>
    <language></language>
    <license></license>
    <source></source>
    <forum></forum>
    <website></website>
  </extension>
</addon>

<addon id="plugin.video.avezy" name="AvEZY" version="1.4.1" provider-name="Wazzu">
	<requires>
		<import addon="xbmc.python" version="2.1.0"/>
		<import addon="program.plexus" />
	</requires>
	<extension point="xbmc.python.pluginsource" library="addon.py">
		<provides>video</provides>
	</extension>
	<extension point="xbmc.addon.metadata">
		<summary>AvEZY</summary>
		<description>Interfaz para ArenaVision desarrollado por Wazzu</description>
		<platform>all</platform>
		<license/>
		<forum/>
		<website/>
		<email>egrueda@gmail.com</email>
		<disclaimer>El autor no aloja ni distribuye cualquier contenido que ud. pudiera reproducir usando este addon. El autor no tiene participacion en el desarrollo de cualquier tecnologia incluida.</disclaimer>
		<source/>
	</extension>
	<extension point="xbmc.addon.repository" name="AvEZY">
		<info compressed="true">https://raw.githubusercontent.com/egrueda/kodi-repo/master/addons.xml</info>
		<checksum>https://raw.githubusercontent.com/egrueda/kodi-repo/master/addons.xml.md5</checksum>
		<datadir zip="true">https://raw.githubusercontent.com/egrueda/kodi-repo/master/zip/</datadir>
	</extension>
</addon>

<addon id="plugin.video.p2psport"
	name="[COLOR green]p2psport[/COLOR]"
	version="0.1.4"
	provider-name="natko1412">
  <requires>
    <import addon="xbmc.python" version="2.1.0"/>
    <import addon="script.module.addon.common" version="2.0.0" />
    <import addon="script.module.requests" />
    <import addon="script.module.beautifulsoup" version="3.2.1"/>
    <import addon="script.module.mechanize" version="0.2.6"/>
  </requires>
  <extension point="xbmc.python.pluginsource" library="default.py">
    <provides>video</provides>
  </extension>
  <extension point="xbmc.addon.metadata">
    <summary>Watch p2p sports in Kodi</summary>
    <platform>all</platform>
    <forum>forums.tvaddons.ag</forum>
  </extension>
</addon>

<addon
  id="plugin.video.SportsDevil"
  version="2018.04.11"
  name="SportsDevil"
  provider-name="SportsDevil">
  <requires>
   <import addon="xbmc.python" version="2.14.0"/>
   <import addon="script.module.dateutil" />
   <import addon="script.module.simplejson" />
   <import addon="script.module.six" />
   <import addon="script.module.requests" />
   <import addon="script.module.streamlink.base" />
   <import addon="plugin.video.f4mTester" />
  </requires>
  <extension
    point="xbmc.python.pluginsource"
    library="default.py">
   <provides>video</provides>
  </extension>
  <extension point="xbmc.service" library="service/streamlink_proxy.py" start="startup" />
  <extension point="xbmc.addon.metadata">
    <summary lang="en">SportsDevil addon</summary>
    <description lang="en">Play videos of different ad-financed sports streaming sites.</description>
	<disclaimer lang="en">SportsDevil does not provide any streams of its own; stream quality, content and copyright are responsibility of the ad-financed source web site. For updates - check the readme.</disclaimer>
    <license>GNU GENERAL PUBLIC LICENSE. Version 2, June 1991</license>
    <platform>all</platform>
  </extension>
</addon>

<addon id="program.plexus"
       name="Plexus"
       version="0.1.7"
       provider-name="enen92, TVAddons, RonnieHD">
  <requires>
    <import addon="xbmc.python" version="2.1.0"/>
    <import addon="script.module.requests" />
  </requires>
  <extension point="xbmc.python.pluginsource"
            library="default.py">
        <provides>executable</provides>
  </extension>

  <extension point="xbmc.addon.metadata">
    <summary>SopCast and AceStream for Kodi</summary>
    <description lang="en">Plexus - Any complex structure containing an intricate network of parts. Plexus brings native peer-to-peer support (AceStream and SopCast) for Kodi Entertainment Center for several platforms.[CR][CR]Documentation: (missing)</description>
    <description lang="pt">Plexus - Uma estrutura complexa constituída por uma rede de partes. O Plexus adiciona suporte peer-to-peer nativo (AceStream e Sopcast) ao Kodi Entertainment Center para várias plataformas.[CR][CR]Documentação: (em falta)</description>
    <description lang="es">Plexus - Una estructura compleja conteniendo una intrincada red de partes. Plexus añade soporte nativo peer-to-peer (AceStream y SopCast) al Centro de Entretenimiento Kodi para varias plataformas.[CR][CR]Documentacion: (falta)</description>
	<disclaimer lang="en">The author does not host nor distribute any of the content you may watch using this addon. The author has no part in the development of any included technologies. When seeking help in Kodi's forum please respect rules (http://kodi.wiki/view/Forum_rules).</disclaimer>
    <disclaimer lang="pt">Os autores não alojam nem distribuem nenhum do conteúdo que poderá ser reproduzido a partir deste addon. Os autores não têm qualquer parte no desenvolvimento de qualquer uma das tecnologias. Se procurar ajuda no fórum oficial do Kodi por favor respeite as regras do fórum (http://kodi.wiki/view/Forum_rules).</disclaimer>
   	<disclaimer lang="es">El autor no aloja ni distribuye cualquier contenido que ud. pudiera reproducir usando este addon. El autor no tiene participacion en el desarrollo de cualquier tecnologia incluida. Cuando requiera ayuda en el foro de Kodi por favor respete las reglas (http://kodi.wiki/view/Forum_rules).</disclaimer>
    <platform>all</platform>
  </extension>
</addon>

<addon id="repository.free" name="[COLOR gold][B]Ike.Free.Repo[/B][/COLOR]" version="0.1" provider-name="[COLOR lime][B]IKE[/B][/COLOR]">
	<extension point="xbmc.addon.repository" name="repository.free">
		<info compressed="false">https://raw.githubusercontent.com/xistra/ufp/master/addons.xml</info>
		<checksum>https://raw.githubusercontent.com/xistra/ufp/master/addons.xml.md5</checksum>
		<datadir zip="true">https://raw.githubusercontent.com/xistra/ufp/master/repo/</datadir>
	</extension>
	<extension point="xbmc.addon.metadata">
		<summary>[COLOR blue][B]Ike.Free.Repo[/B][/COLOR]</summary>
		<description>[COLOR red][B]Ike.Free.Repo[/B][/COLOR]</description>
		<disclaimer></disclaimer>
		<platform>all</platform>
	</extension>
</addon>

<addon id="script.ike.pairwith"
  name="Ike Pair"
  version="5.2"
  provider-name="Ike">
  <requires>
    <import addon="xbmc.python" version="2.1.0"/>
  </requires>
  <extension point="xbmc.python.script" library="addon.py">
    <provides>executable</provides>
  </extension>
  <extension point="xbmc.addon.metadata">
    <platform>all</platform>
    <summary lang="en">Ike Pair</summary>
    <description lang="en">Ike Pair</description>
	<disclaimer>Ike Pair</disclaimer>
  </extension>
</addon>

<addon id="service.ike.autosubs"
    name="Ike AutoSubs" version="1.0" provider-name="Ike">
  <requires>
    <import addon="xbmc.python" version="2.1.0"/>
  </requires>
  <extension point="xbmc.service" library="default.py" start="login" />
  <extension point="xbmc.python.script" library="default.py">
    <provides>all</provides>
  </extension>
  <extension point="xbmc.addon.metadata">
    <summary lang="en">Auto Search for Subtitles on Play</summary>
    <description lang="en">Auto Search for Subtitles on Playback start if no subs are found.[CR][CR]Icon credits goes to zNET Computer Solutions http://www.znetcs.pl</description>
    <summary lang="pt">Pesquisa Automática por legendas no Play</summary>
    <description lang="pt">Pesquisa Automática por legendas na reprodução se não existirem legendas.[CR][CR]Créditos dos icons vão para zNET Computer Solutions http://www.znetcs.pl</description>
    <platform>all</platform>
    <language>pt</language>
  </extension>
</addon>
</addons>
